flycs_sdk/__init__.py
flycs_sdk/custom_code.py
flycs_sdk/entities.py
flycs_sdk/functions.py
flycs_sdk/pipelines.py
flycs_sdk/procedures.py
flycs_sdk/query_base.py
flycs_sdk/query_base_schema.py
flycs_sdk/transformations.py
flycs_sdk/triggers.py
flycs_sdk/views.py
flycs_sdk-0.12.1.dist-info/METADATA
flycs_sdk-0.12.1.dist-info/WHEEL
flycs_sdk-0.12.1.dist-info/LICENSE
flycs_sdk-0.12.1.dist-info/RECORD
