Metadata-Version: 2.1
Name: flycs-sdk
Version: 0.12.1
Summary: Top-level package for Flycs SDK.
Home-page: https://github.com/Fourcast/flycs_sdk
License: MIT
Author: Tristan Van Thielen
Author-email: tristan.van.thielen@devoteam.com
Requires-Python: >=3.8,<3.11
Classifier: Development Status :: 2 - Pre-Alpha
Classifier: Intended Audience :: Developers
Classifier: License :: OSI Approved :: MIT License
Classifier: Natural Language :: English
Classifier: Programming Language :: Python :: 3
Classifier: Programming Language :: Python :: 3.8
Classifier: Programming Language :: Python :: 3.9
Classifier: Programming Language :: Python :: 3.10
Classifier: Programming Language :: Python :: 3
Classifier: Programming Language :: Python :: 3.10
Classifier: Programming Language :: Python :: 3.8
Classifier: Programming Language :: Python :: 3.9
Requires-Dist: pendulum (>=2.1.1,<3.0.0)
Requires-Dist: pytz (==2022.2.1)
Requires-Dist: requirements-parser (>=0.5.0,<0.6.0)
Requires-Dist: ruamel.yaml (>=0.17.0,<0.18.0)
Requires-Dist: semver (==2.13.0)
